<?xml version="1.0" encoding="utf-8" ?>

<ToyIndexCollection>
	<Toys>
		<Info name = "#0 meow meow">
			<Health>50</Health>
			<unlocked>false</unlocked>
			<Description>a cat ?</Description>
		</Info>
		<Info name = "#1 woof woof">
			<Health>60</Health>
			<unlocked>false</unlocked>
			<Description>a dog ?</Description>
		</Info>
		<Info name = "#2 chi chi">
			<Health>40</Health>
			<unlocked>false</unlocked>
			<Description>i really don't know what is this ?</Description>
		</Info>
		<Info name = "#3 kabummm">
			<Health>90</Health>
			<unlocked>false</unlocked>
			<Description>dear lord please save me T_T</Description>
		</Info>
	</Toys>
</ToyIndexCollection>